{
 "absolute_value": 0,
 "align_labels_right": 0,
 "creation": "2025-01-22 11:44:09.643171",
 "css": "/* General Body Styling */\r\nbody {\r\n  margin: 0;\r\n  font-family: 'Arial', sans-serif;\r\n  background: #f9f9f9;\r\n}\r\n\r\n/* Certificate Container Styling */\r\n.certificate-container {\r\n  display: flex;\r\n  justify-content: center;\r\n  align-items: flex-start;  /* Adjusted to align to the top */\r\n  height: auto;\r\n  min-height: 120vh;  /* Increased height to allow for more content */\r\n  background: url('https://sl.bing.net/g0sIAUznGxg') no-repeat center center;\r\n  background-size: cover; /* Ensure the background image scales to cover the element */\r\n}\r\n\r\n/* Certificate Box Styling */\r\n.certificate {\r\n  width: 80%;\r\n  max-width: 800px;\r\n  padding: 80px 50px;  /* Increased padding for more vertical space */\r\n  background: rgba(255, 255, 255, 0.85);\r\n  border: 10px solid #004aad;\r\n  border-radius: 10px;\r\n  text-align: center;\r\n  box-shadow: 0 4px 8px rgba(0, 0, 0, 0.2);\r\n  margin-top: 20px;  /* Added top margin for spacing */\r\n}\r\n\r\n/* Title Styling */\r\n.certificate h2 {\r\n  font-size: 36px;\r\n  color: #004aad;\r\n  margin-bottom: 20px;\r\n}\r\n\r\n.certificate h1 {\r\n  font-size: 48px;\r\n  color: #000;\r\n  margin: 10px 0;\r\n}\r\n\r\n.certificate h3 {\r\n  font-size: 24px;\r\n  color: #333;\r\n  margin: 10px 0;\r\n}\r\n\r\n.certificate p {\r\n  font-size: 18px;\r\n  color: #555;\r\n}\r\n\r\n/* Signature Section Styling */\r\n.signature-section {\r\n  margin-top: 50px;  /* Increased margin for more space */\r\n  text-align: center;\r\n}\r\n\r\n.signature {\r\n  display: inline-block;\r\n  width: 300px;\r\n}\r\n\r\n.signature hr {\r\n  margin: 0 0 10px;\r\n  border: 1px solid #000;\r\n}\r\n\r\n/* Adjustments for Printing */\r\n@media print {\r\n  body {\r\n    margin: 0;\r\n    padding: 0;\r\n  }\r\n\r\n  .certificate-container {\r\n    height: auto;\r\n    background: none; /* Remove background image when printing */\r\n  }\r\n\r\n  .certificate {\r\n    width: 100%;\r\n    max-width: 100%; /* Allow for scaling when printing */\r\n    padding: 50px;\r\n    box-shadow: none; /* Remove box-shadow for printing */\r\n    border: 1px solid #004aad;\r\n  }\r\n\r\n  .certificate h1 {\r\n    font-size: 36px;\r\n  }\r\n\r\n  .certificate h2 {\r\n    font-size: 24px;\r\n  }\r\n\r\n  .certificate p,\r\n  .certificate h3 {\r\n    font-size: 16px;\r\n  }\r\n}\r\n",
 "custom_format": 0,
 "default_print_language": "en",
 "disabled": 0,
 "doc_type": "Participants List",
 "docstatus": 0,
 "doctype": "Print Format",
 "font_size": 14,
 "format_data": "[{\"fieldname\": \"print_heading_template\", \"fieldtype\": \"Custom HTML\", \"options\": \"<div class=\\\"print-heading\\\">\\t\\t\\t\\t<h2><div>CERTIFICATE OF ACHIEVEMENT</div><br><small class=\\\"sub-heading\\\">{{ doc.participant_name }}</small>\\t\\t\\t\\t</h2></div>\"}, {\"fieldtype\": \"Section Break\", \"label\": \"\"}, {\"fieldtype\": \"Column Break\"}, {\"fieldname\": \"_custom_html\", \"print_hide\": 0, \"label\": \"Custom HTML\", \"fieldtype\": \"HTML\", \"options\": \"<!DOCTYPE html>\\r\\n<html lang=\\\"en\\\">\\r\\n<head>\\r\\n  <meta charset=\\\"UTF-8\\\">\\r\\n  <meta name=\\\"viewport\\\" content=\\\"width=device-width, initial-scale=1.0\\\">\\r\\n  <title>Certificate</title>\\r\\n  <link rel=\\\"stylesheet\\\" href=\\\"styles.css\\\">\\r\\n</head>\\r\\n<body>\\r\\n  <div class=\\\"certificate-container\\\">\\r\\n    <div class=\\\"certificate\\\">\\r\\n      <h2>Certificate of Achievement</h2>\\r\\n      <p>This certificate is presented to</p>\\r\\n      <h1>{{doc.participant_name}}</h1>\\r\\n      <p>For outstanding performance in</p>\\r\\n      <h3>{{doc.event}}</h3>\\r\\n      <p>Date: <p>Date: {{ frappe.utils.formatdate(frappe.utils.today(), \\\"MMMM dd, yyyy\\\") }}</p>\\r\\n      <div class=\\\"signature-section\\\">\\r\\n        <div class=\\\"signature\\\">\\r\\n          <hr>\\r\\n          <p>Authorized Signature</p>\\r\\n        </div>\\r\\n      </div>\\r\\n    </div>\\r\\n  </div>\\r\\n</body>\\r\\n</html>\\r\\n\"}]",
 "html": "",
 "idx": 0,
 "line_breaks": 0,
 "margin_bottom": 15.0,
 "margin_left": 15.0,
 "margin_right": 15.0,
 "margin_top": 15.0,
 "modified": "2025-01-31 01:04:29.152229",
 "modified_by": "Administrator",
 "module": "Event Management Systems",
 "name": "Event Certificate",
 "owner": "Administrator",
 "page_number": "Hide",
 "print_format_builder": 0,
 "print_format_builder_beta": 0,
 "print_format_type": "Jinja",
 "raw_printing": 0,
 "show_section_headings": 0,
 "standard": "Yes"
}